pycsql/__init__.py
pycsql/access.py
pycsql/config/__init__.py
pycsql/config/config.py
pycsql/core/__init__.py
pycsql/core/manager.py
pycsql/db/__init__.py
pycsql/db/pycsql.py
PycSQL-1.0.dist-info/LICENSE
PycSQL-1.0.dist-info/METADATA
PycSQL-1.0.dist-info/WHEEL
PycSQL-1.0.dist-info/top_level.txt
PycSQL-1.0.dist-info/RECORD
